simple_learn/__init__.py
simple_learn/version.py
simple_learn/classifiers/__init__.py
simple_learn/classifiers/param_grid.py
simple_learn/classifiers/simple_classifier.py
simple_learn/classifiers/simple_classifier_list.py
simple_learn/encoders/simple_model_encoder.py
simple_learn/regressors/__init__.py
simple_learn/regressors/param_grid.py
simple_learn/regressors/simple_regressor.py
simple_learn/regressors/simple_regressor_list.py
simple_learn/simple_logging/custom_logging.py
simple_learn-1.0.1.dist-info/LICENSE
simple_learn-1.0.1.dist-info/METADATA
simple_learn-1.0.1.dist-info/WHEEL
simple_learn-1.0.1.dist-info/top_level.txt
simple_learn-1.0.1.dist-info/RECORD
