Metadata-Version: 2.1
Name: simple-learn
Version: 1.0.1
Summary: A python package to simplify data modeling.
Home-page: https://github.com/skekre98/simple_learn
Author: Sharvil Kekre
Author-email: sharvildev@gmail.com
License: UNKNOWN
Platform: UNKNOWN
Classifier: Programming Language :: Python :: 3
Classifier: Programming Language :: Python :: 3 :: Only
Classifier: Programming Language :: Python :: 3.6
Classifier: Programming Language :: Python :: 3.7
Classifier: Programming Language :: Python :: 3.8
Classifier: Programming Language :: Python :: 3.9
Classifier: License :: OSI Approved :: MIT License
Classifier: Operating System :: OS Independent
Requires-Python: >=3.6
Requires-Dist: numpy
Requires-Dist: scikit-learn (>=0.23.1)
